canary_cd/__init__.py
canary_cd/database.py
canary_cd/dependencies.py
canary_cd/main.py
canary_cd/models.py
canary_cd/settings.py
canary_cd/routers/__init__.py
canary_cd/routers/auth.py
canary_cd/routers/config.py
canary_cd/routers/deploy.py
canary_cd/routers/page.py
canary_cd/routers/project.py
canary_cd/routers/redirect.py
canary_cd/routers/secret.py
canary_cd/routers/webhook.py
canary_cd/utils/__init__.py
canary_cd/utils/crypto.py
canary_cd/utils/notify.py
canary_cd/utils/pattern.py
canary_cd/utils/tasks.py
canary_cd-0.1.dev3.dist-info/METADATA
canary_cd-0.1.dev3.dist-info/WHEEL
canary_cd-0.1.dev3.dist-info/entry_points.txt
canary_cd-0.1.dev3.dist-info/licenses/LICENSE
canary_cd-0.1.dev3.dist-info/RECORD
