Metadata-Version: 2.4
Name: canary-cd
Version: 0.1.dev3
Summary: Continuous Deployment API for Container and Static Pages
Project-URL: documentation, https://docs.rehborn.dev
Project-URL: source, https://github.com/rehborn/canary-cd.git
Author-email: Dominique Rehborn <dominique@rehborn.dev>
License-Expression: Apache-2.0
License-File: LICENSE
Requires-Python: <3.14,>=3.12
Requires-Dist: docker<8.0.0,>=7.1.0
Requires-Dist: fastapi<0.117.0,>=0.116.1
Requires-Dist: gitpython<4.0.0,>=3.1.44
Requires-Dist: pygithub<3.0.0,>=2.5.0
Requires-Dist: python-dotenv<2.0.0,>=1.0.1
Requires-Dist: python-multipart<0.0.21,>=0.0.20
Requires-Dist: pyyaml<7.0.0,>=6.0.2
Requires-Dist: sqlmodel<0.0.25,>=0.0.24
Requires-Dist: uvicorn<0.36.0,>=0.35.0
